fpql/__init__.py
fpql/bonds.py
fpql/customclass.py
fpql/pricingmodels.py
fpql/pym_ql_utils.py
fpql/pymodels.py
fpql/pytclasses.py
fpql/ql_conventions.py
fpql/ql_enums.py
fpql/ql_interf.py
fpql/ql_utils.py
fpql/samples.py
fpql/stoch_process_class.py
fpql/termstructure.py
fpql-0.4.13.dist-info/METADATA
fpql-0.4.13.dist-info/WHEEL
fpql-0.4.13.dist-info/top_level.txt
fpql-0.4.13.dist-info/RECORD
