Metadata-Version: 2.1
Name: fpql
Version: 0.4.13
Summary: A python package for financial instruments using QuantLib
Home-page: https://github.com/romsey67/fpql-project.git
Author: ROSLI MOHD SANI
Author-email: romsey67@gmail.com
License: UNKNOWN
Platform: UNKNOWN
Classifier: Programming Language :: Python :: 3
Classifier: License :: OSI Approved :: MIT License
Classifier: Operating System :: OS Independent
Requires-Python: >=3.6
Requires-Dist: QuantLib
Requires-Dist: pydantic
Requires-Dist: typing-extensions
Requires-Dist: numpy
Requires-Dist: matplotlib
